<item>
	<title>Balanço da PythonBrasil[5] em Caxias do Sul</title>
	<link>http://pythonrio.org/balanco-da-pythonbrasil5-em-caxias-do-sul</link>
	<pubDate>Thu Sep 24 05:15:00 -0700 2009</pubDate>
	
	<dc:creator><![CDATA[PythOnRio]]></dc:creator>
	
	

	<category><![CDATA[Uncategorized]]></category>

	<category domain="category" nicename="uncategorized"><![CDATA[Uncategorized]]></category>

  <guid isPermaLink="false">http://pythonrio.org/balanco-da-pythonbrasil5-em-caxias-do-sul</guid>
	<description></description>
	<content:encoded><![CDATA[<div style="">Esse ano, a&nbsp;<a href="http://www.pythonbrasil.org.br/2009">confer&ecirc;ncia nacional</a>&nbsp;que reuniu a comunidade brasileira de&nbsp;<a href="http://python.org">Python</a>&nbsp;aconteceu em&nbsp;<a href="http://www.pythonbrasil.org.br/2009/programe-sua-viagem/caxias-do-sul">Caxias do Sul</a>&nbsp;na&nbsp;<a href="http://www.ucs.br/site">Universidade de Caxias do Sul</a>.</div>
<p />
<div style="">A infra-estrutura da universidade &eacute; algo de outro mundo. O campus &eacute; enorme e muito organizado. Para completar, em todo lugar encontramos pessoas sempre muito educadas e sol&iacute;citas. A organiza&ccedil;&atilde;o fez um &oacute;timo trabalho em receber os participantes do evento.</div>
<p />
<div style="">A&nbsp;<a href="http://pythonrio.org">PythOnRio</a>&nbsp;foi presen&ccedil;a marcante no evento. Nem o frio, nem a chuva intimidaram a turma carioca que participou com uma caravana de nada menos que <strong>20</strong> pessoas. Falando em frio, o que passamos no&nbsp;<a href="http://henriquebastos.net/2009/06/30/conclusoes-sobre-o-fisl-10/">FISL 10</a>&nbsp;n&atilde;o foi nada. Em Caxias do Sul, os term&ocirc;metros registravam t&iacute;midos 3 graus.</div>
<p />
<p><a href="http://www.flickr.com/photos/henriquebastos/sets/72157622319271969/" title="Veja algumas fotos no Flickr" target="_blank">
<div style=""><a href="http://www.flickr.com/photos/henriquebastos/3949173175/in/set-72157622319271969/"><img class="posterous_download_image" src="" border="0" height="0" width="0" /></a></div>
</a></p>
<p />
<div style="">Como manda a tradi&ccedil;&atilde;o das confer&ecirc;ncias da comunidade&nbsp;<a href="http://python.org">Python</a>, o n&iacute;vel t&eacute;cnico das palestras foi espetacular. N&atilde;o deixem de ouvir os&nbsp;<a href="http://pt.wikipedia.org/wiki/Podcasting">podcasts</a>&nbsp;que fizemos&nbsp;<em>in loco</em> para registrar os pontos mais marcantes do evento.</div>
<p />
<div style="">Podcast do primeiro dia na PythonBrasil[5]</div>
<p><div class='p_embed p_audio_embed'>
<a href="http://getfile1.posterous.com/getfile/files.posterous.com/pythonrio/F2hvGVrInjKTcmcCFLq7Z2TqwCxZGYjeyUYbR2ijSlk7HtDXS0kY335bUTpD/PythonBrasil5_Dia_1.mp3"><div class='p_icon'></div>
<div class='p_text'><strong>Pythonbrasil (5) Dia 1</strong> by Henrique Bastos</div>
</a></div>
</p>
<p />
<div style="">Podcast do segundo dia na PythonBrasil[5]</div>
<p><div class='p_embed p_audio_embed'>
<a href="http://getfile3.posterous.com/getfile/files.posterous.com/pythonrio/AHVpxLBQDR17RG14Dmf8tAp6Xc33Xn0xsivyyOogrsobRv9IT0hm1K7b1a2B/PythonBrasil5_Dia_2.mp3"><div class='p_icon'></div>
<div class='p_text'><strong>Pythonbrasil (5) Dia 2</strong> by Henrique Bastos</div>
</a></div>
</p>
<p />
<div style="">Al&eacute;m da&nbsp;<a href="http://www.pythonbrasil.org.br/2009/sobre-o-evento/programacao">trilha de palestras</a>, a&nbsp;<a href="http://www.pythonbrasil.org.br/2009">PythonBrasil[5]</a>&nbsp;contou com uma &aacute;rea de&nbsp;<a href="http://www.python.org.br/wiki/OpenSpaces">OpenSpaces</a>&nbsp;e outra com&nbsp;<a href="http://www.pythonbrasil.org.br/2009/sobre-o-evento/mini-cursos">Mini-Cursos</a>. O&nbsp;<a href="http://www.python.org.br/wiki/OpenSpaces">OpenSpaces</a>&nbsp;definitivamente veio para ficar. Foi um sucesso absoluto, e dentre os&nbsp;<a href="http://www.pythonbrasil.org.br/2009/sobre-o-evento/mini-cursos">Mini-Cursos</a>, o da turma da&nbsp;<a href="http://www.pythonbrasil.org.br/2009/sobre-o-evento/inscricoes/b373264e9a460090b72badb71dfc6cf8">PySide</a>&nbsp;falando sobre&nbsp;<a href="http://python.org">Python</a>&nbsp;e&nbsp;<a href="http://pt.wikipedia.org/wiki/Qt">Qt</a>&nbsp;realmente movimentou o pessoal.</div>
<p />
<div style="">Como n&atilde;o podia faltar em uma confer&ecirc;ncia de respeito, tivemos uma edi&ccedil;&atilde;o especial do&nbsp;<a href="http://horaextra.org">#Horaextra</a>&nbsp;onde lotamos uma&nbsp;<a href="http://www.hamburgueriajuventus.com.br/">hamburgueria</a>&nbsp;para tentar espantar o frio. Foi uma confraterniza&ccedil;&atilde;o daquelas! D&ecirc;em uma olhada no v&iacute;deo:</div>
<p />
<div style=""><iframe src="http://player.vimeo.com/video/6731630?portrait=0" frameborder="0" height="393" width="696"></iframe></div>
<p />
<div style="">Desta vez, o evento foi um pouco mais r&aacute;pido pra mim. Precisei voltar para o Rio no s&aacute;bado com o&nbsp;<a href="http://jacobian.org">Jacob Kaplan-Moss</a>&nbsp;para preparar os &uacute;ltimos detalhes do&nbsp;<a href="http://devinrio.com.br">Dev in Rio 2009</a>. Mas os dois dias da PythonBrasil[5] valeram cada instante! &nbsp;Nosso grande amigo e Big Kahuna,&nbsp;<a href="http://softwarelivre.org/profile/deo">Dorneles Trem&eacute;a,</a>&nbsp;junto com toda sua equipe, est&atilde;o de&nbsp;parab&eacute;ns pelo evento!</div>
<p />
<div style="">[]'s,&nbsp;<a href="http://henriquebastos.net">Henrique Bastos</a></div>]]></content:encoded>
	<excerpt:encoded><![CDATA[Esse ano, a conferência nacional que reuniu a comunidade brasileira de Python aconteceu em Caxias do Sul na Universidade de Caxias do Sul. A infra-estrutura da universidade é algo de outro mundo. O campus é enorme e muito organizado. Para completa...]]></excerpt:encoded>	

	<wp:post_date>Thu Sep 24 05:15:00 -0700 2009</wp:post_date>
	<wp:post_date_gmt>Thu Sep 24 05:15:00 -0700 2009</wp:post_date_gmt>
	<wp:comment_status>open</wp:comment_status>
	<wp:ping_status>open</wp:ping_status>
	<wp:post_id>4504653</wp:post_id>
	<wp:post_name>balanco-da-pythonbrasil5-em-caxias-do-sul</wp:post_name>
	<wp:status>publish</wp:status>
	<wp:post_parent>0</wp:post_parent>
	<wp:menu_order>0</wp:menu_order>
	<wp:post_type>post</wp:post_type>
	<wp:post_password></wp:post_password>
	<wp:is_sticky>0</wp:is_sticky>

	
		<wp:comment>
			<wp:comment_id>982257</wp:comment_id>
			
				<wp:comment_author><![CDATA[Francisco Souza]]></wp:comment_author>
				<wp:comment_author_url><![CDATA[http://blog.franciscosouza.net]]></wp:comment_author_url>
			
			<wp:comment_date>Thu Sep 24 12:16:12 -0700 2009</wp:comment_date>
			<wp:comment_date_gmt>Thu Sep 24 12:16:12 -0700 2009</wp:comment_date_gmt>
			<wp:comment_content><![CDATA[Legal legal, valeu por compartilhar a experiência. Ano que vem eu quero ir /)

Devinrio também \o/

Abraços! ;D]]></wp:comment_content>
			<wp:comment_approved>1</wp:comment_approved>
			<wp:comment_type></wp:comment_type>
			<wp:comment_parent>0</wp:comment_parent>
		</wp:comment>
	
		<wp:comment>
			<wp:comment_id>982871</wp:comment_id>
			
				<wp:comment_author><![CDATA[Jonh Edson]]></wp:comment_author>
				<wp:comment_author_url><![CDATA[]]></wp:comment_author_url>
			
			<wp:comment_date>Thu Sep 24 13:48:29 -0700 2009</wp:comment_date>
			<wp:comment_date_gmt>Thu Sep 24 13:48:29 -0700 2009</wp:comment_date_gmt>
			<wp:comment_content><![CDATA[Boa Henrique!!!! Fiz uma seleção de fotos de várias pessoas mas ainda não tinha tido tempo para criar o Post, vou lhe enviar a minha seleção e você complementa com as fotos. Nota DEZ o seu post!!!
[]'s
Jonh Edson]]></wp:comment_content>
			<wp:comment_approved>1</wp:comment_approved>
			<wp:comment_type></wp:comment_type>
			<wp:comment_parent>0</wp:comment_parent>
		</wp:comment>
	
		<wp:comment>
			<wp:comment_id>990909</wp:comment_id>
			
				<wp:comment_author><![CDATA[Rudá Porto Filgueiras]]></wp:comment_author>
				<wp:comment_author_url><![CDATA[http://python-blog.blogspot.com/]]></wp:comment_author_url>
			
			<wp:comment_date>Fri Sep 25 07:06:23 -0700 2009</wp:comment_date>
			<wp:comment_date_gmt>Fri Sep 25 07:06:23 -0700 2009</wp:comment_date_gmt>
			<wp:comment_content><![CDATA[Parabéns pelo vídeo, audio e o post. Acho que para o ano que vem, ter uma &quot;equipe&quot; (mesmo informal) para filmar os &quot;Open Spaces&quot; seria uma grande novidade. :-)]]></wp:comment_content>
			<wp:comment_approved>1</wp:comment_approved>
			<wp:comment_type></wp:comment_type>
			<wp:comment_parent>0</wp:comment_parent>
		</wp:comment>
	
		<wp:comment>
			<wp:comment_id>1136647</wp:comment_id>
			
				<wp:comment_author><![CDATA[caike]]></wp:comment_author>
				<wp:comment_author_url><![CDATA[caikesouza.com]]></wp:comment_author_url>
			
			<wp:comment_date>Wed Oct 07 06:21:54 -0700 2009</wp:comment_date>
			<wp:comment_date_gmt>Wed Oct 07 06:21:54 -0700 2009</wp:comment_date_gmt>
			<wp:comment_content><![CDATA[Parabéns, pessoal !! Excelente cobertura ! 
PythonRio sempre presente. 
Abraço!]]></wp:comment_content>
			<wp:comment_approved>1</wp:comment_approved>
			<wp:comment_type></wp:comment_type>
			<wp:comment_parent>0</wp:comment_parent>
		</wp:comment>
	
</item>
